CHANGELOG.txt
LICENSE
MANIFEST.in
README.txt
setup.py
poweruse/__init__.py
poweruse.egg-info/PKG-INFO
poweruse.egg-info/SOURCES.txt
poweruse.egg-info/dependency_links.txt
poweruse.egg-info/top_level.txt