Metadata-Version: 2.1
Name: poweruse
Version: 0.0.7
Summary: Simplyfied Library.
Author: Spar (Naitik)
Author-email: <pycodermaximos@gmail.com>
License: UNKNOWN
Keywords: python,math,cmath,eazy,easy,better
Platform: UNKNOWN
Classifier: Development Status :: 1 - Planning
Classifier: Intended Audience :: Developers
Classifier: Programming Language :: Python :: 3
Classifier: Operating System :: Unix
Classifier: Operating System :: MacOS :: MacOS X
Classifier: Operating System :: Microsoft :: Windows
License-File: LICENSE
